messagemedia_simple/__init__.py
messagemedia_simple/messages_api.py
messagemedia_simple-1.0.1.dist-info/WHEEL
messagemedia_simple-1.0.1.dist-info/METADATA
messagemedia_simple-1.0.1.dist-info/RECORD
