Metadata-Version: 2.1
Name: messagemedia-simple
Version: 1.0.1
Summary: Simple MessageMedia module for sending SMS messages.
Home-page: https://github.com/mludvig/messagemedia-simple
License: MIT
Keywords: messagemedia,sms
Author: Michael Ludvig
Author-email: mludvig@logix.net.nz
Requires-Python: >=3.6,<4.0
Classifier: License :: OSI Approved :: MIT License
Classifier: Programming Language :: Python :: 3
Classifier: Programming Language :: Python :: 3.6
Classifier: Programming Language :: Python :: 3.7
Classifier: Programming Language :: Python :: 3.8
Requires-Dist: requests (>=2.22.0,<3.0.0)
Project-URL: Repository, https://github.com/mludvig/messagemedia-simple
